AUTHORS
LICENSE
MANIFEST.in
README.rst
setup.cfg
setup.py
carga/__init__.py
carga/carga-dc4-20140210.py
carga/forms.py
carga/models.py
carga/teste-carga-inventario.py
carga/urls.py
carga/views.py
configuracao/__init__.py
configuracao/admin.py
configuracao/forms.py
configuracao/models.py
configuracao/tests.py
configuracao/urls.py
configuracao/views.py
configuracao/fixtures/auth_user.yaml
configuracao/fixtures/auth_user_superuser.yaml
configuracao/fixtures/initial_data.yaml
configuracao/management/__init__.py
configuracao/management/commands/__init__.py
configuracao/management/commands/criarsistema.py
configuracao/migrations/0001_initial.py
configuracao/migrations/0002_layoutlink_layoutlinkfooter_layoutlinkheader_layoutlogo_layoutpagina.py
configuracao/migrations/__init__.py
configuracao/static/css/base-print.css
configuracao/static/css/base.css
configuracao/static/css/changelists.css
configuracao/static/css/colorpicker.css
configuracao/static/css/dashboard.css
configuracao/static/css/forms.css
configuracao/static/css/global.css
configuracao/static/css/ie.css
configuracao/static/css/import-export-admin.css
configuracao/static/css/jquery-ui.min.css
configuracao/static/css/layout.css
configuracao/static/css/login.css
configuracao/static/css/mensagem.css
configuracao/static/css/monitor.css
configuracao/static/css/null.css
configuracao/static/css/patch-iewin.css
configuracao/static/css/pdf.css
configuracao/static/css/pdf_weasy.css
configuracao/static/css/racks.css
configuracao/static/css/relatorios.css
configuracao/static/css/rtl.css
configuracao/static/css/widgets.css
configuracao/static/img/1u.png
configuracao/static/img/arquivo.png
configuracao/static/img/azul.png
configuracao/static/img/entrada.png
configuracao/static/img/favicon.png
configuracao/static/img/icon-pdf.png
configuracao/static/img/icon_arquivo_documento.png
configuracao/static/img/icon_calendar.gif
configuracao/static/img/icon_clock.gif
configuracao/static/img/icon_height_alfa.png
django_arquea.egg-info/PKG-INFO
django_arquea.egg-info/SOURCES.txt
django_arquea.egg-info/dependency_links.txt
django_arquea.egg-info/not-zip-safe
django_arquea.egg-info/requires.txt
django_arquea.egg-info/top_level.txt
