Metadata-Version: 1.0
Name: django-arquea
Version: 2.4.17
Summary: Sistema administrativo do ANSP
Home-page: http://www.ansp.br
Author: NARA
Author-email: noc@ansp.br
License: UNKNOWN
Platform: UNKNOWN
